illallangi/data/aviation/__init__.py
illallangi/data/aviation/__version__.py
illallangi/data/aviation/apps.py
illallangi/data/aviation/adapters/__init__.py
illallangi/data/aviation/adapters/aviation.py
illallangi/data/aviation/admin/__init__.py
illallangi/data/aviation/admin/airline.py
illallangi/data/aviation/admin/airport.py
illallangi/data/aviation/admin/alliance.py
illallangi/data/aviation/checks/__init__.py
illallangi/data/aviation/checks/aviation.py
illallangi/data/aviation/checks/rdf.py
illallangi/data/aviation/diffsyncmodels/__init__.py
illallangi/data/aviation/diffsyncmodels/airline.py
illallangi/data/aviation/diffsyncmodels/airport.py
illallangi/data/aviation/migrations/0001_initial.py
illallangi/data/aviation/migrations/__init__.py
illallangi/data/aviation/models/__init__.py
illallangi/data/aviation/models/airline.py
illallangi/data/aviation/models/airport.py
illallangi/data/aviation/models/alliance.py
illallangi/data/aviation/static/aviation/airlines.jpg
illallangi/data/aviation/static/aviation/airplanes.jpg
illallangi/data/aviation/static/aviation/airports.jpg
illallangi/data/aviation/static/aviation/alliances.jpg
illallangi/data/aviation/static/aviation/airline_logos/3k.png
illallangi/data/aviation/static/aviation/airline_logos/9w.png
illallangi/data/aviation/static/aviation/airline_logos/aa.png
illallangi/data/aviation/static/aviation/airline_logos/ae.png
illallangi/data/aviation/static/aviation/airline_logos/ba.png
illallangi/data/aviation/static/aviation/airline_logos/cx.png
illallangi/data/aviation/static/aviation/airline_logos/cy.png
illallangi/data/aviation/static/aviation/airline_logos/dj.png
illallangi/data/aviation/static/aviation/airline_logos/ek.png
illallangi/data/aviation/static/aviation/airline_logos/ey.png
illallangi/data/aviation/static/aviation/airline_logos/g3.png
illallangi/data/aviation/static/aviation/airline_logos/ib.png
illallangi/data/aviation/static/aviation/airline_logos/ie.png
illallangi_data_aviation-0.4.0.dist-info/METADATA
illallangi_data_aviation-0.4.0.dist-info/WHEEL
illallangi_data_aviation-0.4.0.dist-info/entry_points.txt
illallangi_data_aviation-0.4.0.dist-info/licenses/LICENSE
illallangi_data_aviation-0.4.0.dist-info/RECORD
